<?xml version="1.0" encoding="UTF-8" ?>
<!DOCTYPE mapper PUBLIC "-//mybatis.org//DTD Mapper 3.0//EN" "http://mybatis.org/dtd/mybatis-3-mapper.dtd" >
<mapper namespace="com.less.zhiro.dao.JurisdictionInfoMapper" >
  <resultMap id="BaseResultMap" type="com.less.zhiro.entity.JurisdictionInfo" >
    <!--
      WARNING - @mbggenerated
      This element is automatically generated by MyBatis Generator, do not modify.
    -->
    <id column="jurisdictionid" property="jurisdictionid" jdbcType="INTEGER" />
    <result column="menuid" property="menuid" jdbcType="INTEGER" />
    <result column="auth" property="auth" jdbcType="VARCHAR" />
    <result column="comment" property="comment" jdbcType="VARCHAR" />
    <result column="parent" property="parent" jdbcType="INTEGER" />
  </resultMap>
  <delete id="deleteByPrimaryKey" parameterType="java.lang.Integer" >
    <!--
      WARNING - @mbggenerated
      This element is automatically generated by MyBatis Generator, do not modify.
    -->
    delete from jurisdiction_info
    where jurisdictionid = #{jurisdictionid,jdbcType=INTEGER}
  </delete>
  <insert id="insert" parameterType="com.less.zhiro.entity.JurisdictionInfo" >
    <!--
      WARNING - @mbggenerated
      This element is automatically generated by MyBatis Generator, do not modify.
    -->
    insert into jurisdiction_info (jurisdictionid, menuid, auth, 
      comment, parent)
    values (#{jurisdictionid,jdbcType=INTEGER}, #{menuid,jdbcType=INTEGER}, #{auth,jdbcType=VARCHAR}, 
      #{comment,jdbcType=VARCHAR}, #{parent,jdbcType=INTEGER})
  </insert>
  <update id="updateByPrimaryKey" parameterType="com.less.zhiro.entity.JurisdictionInfo" >
    <!--
      WARNING - @mbggenerated
      This element is automatically generated by MyBatis Generator, do not modify.
    -->
    update jurisdiction_info
    set menuid = #{menuid,jdbcType=INTEGER},
      auth = #{auth,jdbcType=VARCHAR},
      comment = #{comment,jdbcType=VARCHAR},
      parent = #{parent,jdbcType=INTEGER}
    where jurisdictionid = #{jurisdictionid,jdbcType=INTEGER}
  </update>
  <select id="selectByPrimaryKey" resultMap="BaseResultMap" parameterType="java.lang.Integer" >
    <!--
      WARNING - @mbggenerated
      This element is automatically generated by MyBatis Generator, do not modify.
    -->
    select jurisdictionid, menuid, auth, comment, parent
    from jurisdiction_info
    where jurisdictionid = #{jurisdictionid,jdbcType=INTEGER}
  </select>
  <select id="selectAll" resultMap="BaseResultMap" >
    <!--
      WARNING - @mbggenerated
      This element is automatically generated by MyBatis Generator, do not modify.
    -->
    select jurisdictionid, menuid, auth, comment, parent
    from jurisdiction_info
  </select>
</mapper>